odoo/addons/stock_request_purchase/README.rst
odoo/addons/stock_request_purchase/__init__.py
odoo/addons/stock_request_purchase/__manifest__.py
odoo/addons/stock_request_purchase/i18n/de.po
odoo/addons/stock_request_purchase/i18n/es.po
odoo/addons/stock_request_purchase/i18n/it.po
odoo/addons/stock_request_purchase/i18n/stock_request_purchase.pot
odoo/addons/stock_request_purchase/i18n/zh_CN.po
odoo/addons/stock_request_purchase/models/__init__.py
odoo/addons/stock_request_purchase/models/purchase_order.py
odoo/addons/stock_request_purchase/models/purchase_order_line.py
odoo/addons/stock_request_purchase/models/stock_request.py
odoo/addons/stock_request_purchase/models/stock_request_order.py
odoo/addons/stock_request_purchase/models/stock_rule.py
odoo/addons/stock_request_purchase/readme/CONTRIBUTORS.rst
odoo/addons/stock_request_purchase/readme/DESCRIPTION.rst
odoo/addons/stock_request_purchase/readme/ROADMAP.rst
odoo/addons/stock_request_purchase/readme/USAGE.rst
odoo/addons/stock_request_purchase/security/ir.model.access.csv
odoo/addons/stock_request_purchase/static/description/icon.png
odoo/addons/stock_request_purchase/static/description/index.html
odoo/addons/stock_request_purchase/tests/__init__.py
odoo/addons/stock_request_purchase/tests/test_stock_request_purchase.py
odoo/addons/stock_request_purchase/views/purchase_order_views.xml
odoo/addons/stock_request_purchase/views/stock_request_order_views.xml
odoo/addons/stock_request_purchase/views/stock_request_views.xml
odoo14_addon_stock_request_purchase-14.0.1.2.2.dist-info/METADATA
odoo14_addon_stock_request_purchase-14.0.1.2.2.dist-info/WHEEL
odoo14_addon_stock_request_purchase-14.0.1.2.2.dist-info/top_level.txt
odoo14_addon_stock_request_purchase-14.0.1.2.2.dist-info/RECORD
