Metadata-Version: 2.1
Name: odoo14-addon-stock_request_purchase
Version: 14.0.1.2.2
Summary: Internal request for stock
Home-page: https://github.com/OCA/stock-logistics-warehouse
Author: ForgeFlow, Odoo Community Association (OCA)
Author-email: support@odoo-community.org
License: LGPL-3
Classifier: Programming Language :: Python
Classifier: Framework :: Odoo
Classifier: Framework :: Odoo :: 14.0
Classifier: License :: OSI Approved :: GNU Lesser General Public License v3 (LGPLv3)
Requires-Python: >=3.6
Requires-Dist: odoo14-addon-stock-request
Requires-Dist: odoo <14.1dev,>=14.0a
